Metadata-Version: 1.0
Name: CheckingPyTest1
Version: 18.0
Summary: Linear Algebra
Home-page: UNKNOWN
Author: UNKNOWN
Author-email: UNKNOWN
License: UNKNOWN
Platform: UNKNOWN
